ethpector/__init__.py
ethpector/analysis.py
ethpector/main.py
ethpector/abi/__init__.py
ethpector/abi/abi.py
ethpector/assembly/__init__.py
ethpector/assembly/analysis.py
ethpector/assembly/flow.py
ethpector/assembly/metadata.py
ethpector/assembly/program.py
ethpector/classify/__init__.py
ethpector/classify/classification.py
ethpector/classify/parser.py
ethpector/config/__init__.py
ethpector/config/config.py
ethpector/data/__init__.py
ethpector/data/base.py
ethpector/data/datatypes.py
ethpector/data/etherscan.py
ethpector/data/ipfs.py
ethpector/data/node.py
ethpector/data/provider.py
ethpector/data/signatures.py
ethpector/data/sourcify.py
ethpector/data/swarm.py
ethpector/symbolic/__init__.py
ethpector/symbolic/analysis.py
ethpector/symbolic/modules/__init__.py
ethpector/symbolic/modules/extractor.py
ethpector/symbolic/modules/sender.py
ethpector/utils/__init__.py
ethpector/utils/utils.py
ethpector-0.1.8.dist-info/LICENSE.txt
ethpector-0.1.8.dist-info/METADATA
ethpector-0.1.8.dist-info/WHEEL
ethpector-0.1.8.dist-info/entry_points.txt
ethpector-0.1.8.dist-info/top_level.txt
ethpector-0.1.8.dist-info/RECORD
