Metadata-Version: 2.1
Name: ethpector
Version: 0.1.8
Summary: Ethpector extracts useful information from smart contracts.
Home-page: https://github.com/uibk-ethpector/ethpector/
Author: soad003
Author-email: michael.froewis@gmx.at
License: MIT
Project-URL: Documentation, https://uibk-ethpector.github.io/ethpector/
Project-URL: Source, https://github.com/uibk-ethpector/ethpector/
Project-URL: Changelog, https://github.com/uibk-ethpector/ethpector/blob/main/CHANGELOG.rst
Project-URL: Download, https://pypi.org/project/ethpector/#files
Platform: any
Classifier: Development Status :: 4 - Beta
Classifier: Programming Language :: Python
Classifier: Intended Audience :: Developers
Classifier: Intended Audience :: Education
Classifier: Intended Audience :: Science/Research
Classifier: License :: OSI Approved :: MIT License
Classifier: Topic :: Software Development :: Disassemblers
Classifier: Topic :: Utilities
License-File: LICENSE.txt
Requires-Dist: mythril (==0.22.40)
Requires-Dist: pydantic (>=1.9.0)
Requires-Dist: pyevmasm (>=0.2.3)
Requires-Dist: web3 (>=5.28.0)
Requires-Dist: etherscan-python (>=2.1.0)
Requires-Dist: requests (>=2.27.1)
Requires-Dist: diskcache (>=5.4.0)
Requires-Dist: cbor2 (>=5.4.2)
Requires-Dist: python-dotenv (>=0.19.2)
Requires-Dist: eth-abi (>=2.1.1)
Requires-Dist: pyPEG2 (>=2.15.2)
Requires-Dist: pyvis (>=0.2.0)
Requires-Dist: networkx (>=2.8.0)
Requires-Dist: netgraph (>=4.4.1)
Requires-Dist: pydot (==1.4.2)
Requires-Dist: importlib-metadata ; python_version < "3.8"
Provides-Extra: dev
Requires-Dist: pytest ; extra == 'dev'
Requires-Dist: pytest-cov ; extra == 'dev'
Requires-Dist: flake8 (==4.0.1) ; extra == 'dev'
Requires-Dist: flake8-comprehensions (==3.8.0) ; extra == 'dev'
Requires-Dist: black (==22.3.0) ; extra == 'dev'
Requires-Dist: tox ; extra == 'dev'
Requires-Dist: pre-commit ; extra == 'dev'
Requires-Dist: setuptools-scm ; extra == 'dev'
Provides-Extra: testing
Requires-Dist: setuptools ; extra == 'testing'
Requires-Dist: pytest ; extra == 'testing'
Requires-Dist: pytest-cov ; extra == 'testing'
